JiqiZhixin2019GaofenJiaochengGongjuJiJiqiao/README.md
JiqiZhixin2019GaofenJiaochengGongjuJiJiqiao/__init__.py
JiqiZhixin2019GaofenJiaochengGongjuJiJiqiao/__main__.py
JiqiZhixin2019GaofenJiaochengGongjuJiJiqiao/file.epub
JiqiZhixin2019GaofenJiaochengGongjuJiJiqiao/index.html
JiqiZhixin2019GaofenJiaochengGongjuJiJiqiao/css/__init__.py
JiqiZhixin2019GaofenJiaochengGongjuJiJiqiao/css/annotations.css
JiqiZhixin2019GaofenJiaochengGongjuJiJiqiao/css/main.css
JiqiZhixin2019GaofenJiaochengGongjuJiJiqiao/css/normalize.css
JiqiZhixin2019GaofenJiaochengGongjuJiJiqiao/css/popup.css
JiqiZhixin2019GaofenJiaochengGongjuJiJiqiao/font/__init__.py
JiqiZhixin2019GaofenJiaochengGongjuJiJiqiao/font/fontello.eot
JiqiZhixin2019GaofenJiaochengGongjuJiJiqiao/font/fontello.svg
JiqiZhixin2019GaofenJiaochengGongjuJiJiqiao/font/fontello.ttf
JiqiZhixin2019GaofenJiaochengGongjuJiJiqiao/font/fontello.woff
JiqiZhixin2019GaofenJiaochengGongjuJiJiqiao/img/__init__.py
JiqiZhixin2019GaofenJiaochengGongjuJiJiqiao/img/annotator-glyph-sprite.png
JiqiZhixin2019GaofenJiaochengGongjuJiJiqiao/img/annotator-icon-sprite.png
JiqiZhixin2019GaofenJiaochengGongjuJiJiqiao/img/apple-touch-icon.png
JiqiZhixin2019GaofenJiaochengGongjuJiJiqiao/img/cancelfullscreen.png
JiqiZhixin2019GaofenJiaochengGongjuJiJiqiao/img/close.png
JiqiZhixin2019GaofenJiaochengGongjuJiJiqiao/img/fullscreen.png
JiqiZhixin2019GaofenJiaochengGongjuJiJiqiao/img/loader.gif
JiqiZhixin2019GaofenJiaochengGongjuJiJiqiao/img/menu-icon.png
JiqiZhixin2019GaofenJiaochengGongjuJiJiqiao/img/save.png
JiqiZhixin2019GaofenJiaochengGongjuJiJiqiao/img/saved.png
JiqiZhixin2019GaofenJiaochengGongjuJiJiqiao/img/settings-s.png
JiqiZhixin2019GaofenJiaochengGongjuJiJiqiao/img/settings.png
JiqiZhixin2019GaofenJiaochengGongjuJiJiqiao/img/star.png
JiqiZhixin2019GaofenJiaochengGongjuJiJiqiao/js/__init__.py
JiqiZhixin2019GaofenJiaochengGongjuJiJiqiao/js/epub.js
JiqiZhixin2019GaofenJiaochengGongjuJiJiqiao/js/epub.min.js
jiqi_zhixin_2019_gaofen_jiaocheng_gongju_ji_jiqiao-2024.3.5.0.dist-info/METADATA
jiqi_zhixin_2019_gaofen_jiaocheng_gongju_ji_jiqiao-2024.3.5.0.dist-info/WHEEL
jiqi_zhixin_2019_gaofen_jiaocheng_gongju_ji_jiqiao-2024.3.5.0.dist-info/entry_points.txt
jiqi_zhixin_2019_gaofen_jiaocheng_gongju_ji_jiqiao-2024.3.5.0.dist-info/top_level.txt
jiqi_zhixin_2019_gaofen_jiaocheng_gongju_ji_jiqiao-2024.3.5.0.dist-info/RECORD
